nowfocus/__init__.py
nowfocus/__main__.py
nowfocus/conf.py
nowfocus/example-todo.txt
nowfocus/install.py
nowfocus/new_task_dialog.py
nowfocus/session_edit_dialog.py
nowfocus/session_options.py
nowfocus/sessions.csv
nowfocus/settings.py
nowfocus/styles.css
nowfocus/task_window.py
nowfocus/upgrade.py
nowfocus/user_idle_time.py
nowfocus/utils.py
nowfocus/connectors/activitywatch.py
nowfocus/connectors/caldav.py
nowfocus/connectors/csv.py
nowfocus/connectors/psc_timetracker.py
nowfocus/connectors/taskwarrior.py
nowfocus/connectors/timewarrior.py
nowfocus/connectors/todo_template.py
nowfocus/connectors/todotxt.py
nowfocus/connectors/trello.py
nowfocus/connectors/txt.py
nowfocus/connectors/vikunja.py
nowfocus/desktop-extras/nowfocus.desktop
nowfocus/desktop-extras/nowfocus.png
nowfocus/desktop-extras/nowfocus.svg
nowfocus/icon/cancel.png
nowfocus/icon/cancel.svg
nowfocus/icon/edit.png
nowfocus/icon/edit.svg
nowfocus/icon/icon-0.svg
nowfocus/icon/icon-1.svg
nowfocus/icon/icon-2.svg
nowfocus/icon/icon-3.svg
nowfocus/icon/icon-4.svg
nowfocus/icon/icon-5.svg
nowfocus/icon/icon-6.svg
nowfocus/icon/icon-7.svg
nowfocus/icon/icon-8.svg
nowfocus/icon/icon-9.svg
nowfocus/icon/icon-red.svg
nowfocus/icon/icon.svg
nowfocus/icon/mark-done.png
nowfocus/icon/mark-done.svg
nowfocus/icon/pause.png
nowfocus/icon/pause.svg
nowfocus/icon/settings.png
nowfocus/icon/settings.svg
nowfocus/sound/bell-xylophone-g.mp3
nowfocus/sound/dinner-bell.mp3
nowfocus/sound/xylophone-chord.mp3
nowfocus-0.5.7.dist-info/licenses/LICENSE
nowfocus-0.5.7.dist-info/METADATA
nowfocus-0.5.7.dist-info/WHEEL
nowfocus-0.5.7.dist-info/entry_points.txt
nowfocus-0.5.7.dist-info/top_level.txt
nowfocus-0.5.7.dist-info/RECORD
