Metadata-Version: 2.4
Name: nowfocus
Version: 0.5.7
Summary: nowfocus: the open source task-tracking self-control panel.
Author: AltruistEnterprises
Project-URL: Homepage, https://www.nowfocus.org
Project-URL: repository, https://codeberg.org/AltruistEnterprises/nowfocus
Classifier: Programming Language :: Python :: 3
Classifier: Operating System :: OS Independent
Classifier: License :: OSI Approved :: GNU General Public License v3 or later (GPLv3+)
Classifier: Environment :: X11 Applications :: GTK
Classifier: Intended Audience :: End Users/Desktop
License-File: LICENSE
Requires-Dist: psutil
Requires-Dist: pygobject==3.50.0
Requires-Dist: pycairo==1.27
Requires-Dist: attrs
Requires-Dist: caldav
Requires-Dist: certifi
Requires-Dist: charset-normalizer
Requires-Dist: icalendar
Requires-Dist: idna
Requires-Dist: pywin32>=221; platform_system == "Windows"
Requires-Dist: kitchen
Requires-Dist: lxml
Requires-Dist: playsound3
Requires-Dist: python-dateutil
Requires-Dist: pytodotxt
Requires-Dist: pytz
Requires-Dist: recurring-ical-events
Requires-Dist: requests
Requires-Dist: setproctitle
Requires-Dist: setuptools
Requires-Dist: six
Requires-Dist: taskw
Requires-Dist: timew
Requires-Dist: tzlocal
Requires-Dist: urllib3
Requires-Dist: vobject
Requires-Dist: x-wr-timezone
Dynamic: license-file
